pytorch_probing/__init__.py
pytorch_probing/module_wrapper.py
pytorch_probing/parallel_module_dict.py
pytorch_probing/py.typed
pytorch_probing/collect/__init__.py
pytorch_probing/collect/collect.py
pytorch_probing/collect/collected_dataset.py
pytorch_probing/interceptor/__init__.py
pytorch_probing/interceptor/interceptor.py
pytorch_probing/interceptor/interceptor_layer.py
pytorch_probing/prober/__init__.py
pytorch_probing/prober/prober.py
pytorch_probing-0.1.1.dist-info/LICENSE
pytorch_probing-0.1.1.dist-info/METADATA
pytorch_probing-0.1.1.dist-info/WHEEL
pytorch_probing-0.1.1.dist-info/top_level.txt
pytorch_probing-0.1.1.dist-info/RECORD
