Metadata-Version: 2.1
Name: pytorch_probing
Version: 0.1.1
Summary: PyTorch-Probing is a framework for probing PyTorch models internal functioning.
Home-page: https://github.com/H-IAAC/pytorch-probing
Author: EltonCN, H.IAAC
Author-email: elton.nascimento@students.ic.unicamp.br, hiaac@unicamp.br
License: LGPLv3
Project-URL: Bug Tracker, https://github.com/H-IAAC/pytorch-probing/issues
Project-URL: Documentation, https://h-iaac.github.io/pytorch-probing/
Classifier: Programming Language :: Python :: 3
Classifier: Operating System :: OS Independent
Classifier: Topic :: Scientific/Engineering
Classifier: Topic :: Scientific/Engineering :: Artificial Intelligence
Classifier: Intended Audience :: Science/Research
Classifier: License :: OSI Approved :: GNU Lesser General Public License v3 (LGPLv3)
License-File: LICENSE
Requires-Dist: numpy<2.0
Requires-Dist: torch
Provides-Extra: doc_generation
Requires-Dist: sphinx; extra == "doc-generation"
Requires-Dist: sphinx-rtd-theme; extra == "doc-generation"
Requires-Dist: nbsphinx; extra == "doc-generation"
Requires-Dist: sphinx-mdinclude==0.5.4; extra == "doc-generation"
Provides-Extra: tests
Requires-Dist: mypy; extra == "tests"
Requires-Dist: testbook; extra == "tests"
Requires-Dist: ipython; extra == "tests"
Requires-Dist: ipykernel; extra == "tests"
